[{"id":"68df4a24.700014","type":"modbustcp-read","z":"ee314869.f86738","name":"UGT509 (Ultrasonic Sensor)","dataType":"HoldingRegister","adr":"7002","quantity":"1","rate":"0.5","server":"8bde0f02.d34bd","x":209.99998474121094,"y":75.00000381469727,"wires":[["f501be75.92e66"]]},{"id":"c76ca4fb.09f368","type":"mqtt out","z":"ee314869.f86738","name":"","topic":"/v1/{your Device Id}/data","qos":"","retain":"","broker":"3b957dc9.63628a","x":902.75,"y":314.19447326660156,"wires":[]},{"id":"a6ffe5ed.8948d8","type":"function","z":"ee314869.f86738","name":"relayr Payload Formatting","func":"msg.payload = {\n    meaning: 'proximity',\n    value: msg.payload\n}\nreturn msg;","outputs":1,"noerr":0,"x":695.7222290039062,"y":257.02777099609375,"wires":[["c76ca4fb.09f368"]]},{"id":"f501be75.92e66","type":"function","z":"ee314869.f86738","name":"Read Distance","func":"msg.payload = msg.payload[0];\nreturn msg;","outputs":1,"noerr":0,"x":388.1944274902344,"y":141.75,"wires":[["781acd14.1ef4dc"]]},{"id":"d12f68d.dd76a98","type":"modbustcp-read","z":"ee314869.f86738","name":"TA2105 (Temperature Sensor)","dataType":"HoldingRegister","adr":"3002","quantity":"1","rate":"1","server":"39858602.52a1a2","x":211.5,"y":349.3221740722656,"wires":[["d6959ec0.107408"]]},{"id":"9a8108ae.4dee","type":"function","z":"ee314869.f86738","name":"relayr Payload Formatting","func":"msg.payload = {\n    meaning: 'temperature',\n    value: msg.payload/10\n}\nreturn msg;","outputs":1,"noerr":0,"x":548.9722442626953,"y":484.3500061035156,"wires":[["43b7a37f.3026c4"]]},{"id":"d6959ec0.107408","type":"function","z":"ee314869.f86738","name":"Read Temperature","func":"msg.payload = msg.payload[0];\nreturn msg;","outputs":1,"noerr":0,"x":380.4444580078125,"y":420.57220458984375,"wires":[["9a8108ae.4dee","8d1fb3e1.5e5108"]]},{"id":"43b7a37f.3026c4","type":"mqtt out","z":"ee314869.f86738","name":"","topic":"/v1/{your Device Id}/data","qos":"","retain":"","broker":"3b957dc9.63628a","x":750.5000152587891,"y":550.5722045898438,"wires":[]},{"id":"8d1fb3e1.5e5108","type":"debug","z":"ee314869.f86738","name":"","active":false,"console":"false","complete":"payload","x":613.7221832275391,"y":384.2499694824219,"wires":[]},{"id":"a664dd2.493bd2","type":"modbustcp-read","z":"ee314869.f86738","name":"KQ5100 (Capacitive Sensor)","dataType":"HoldingRegister","adr":"4002","quantity":"1","rate":"0.5","server":"a1959601.692438","x":209.49998474121094,"y":608,"wires":[["c23e79f0.d14e"]]},{"id":"14f1bbc7.9e90c4","type":"mqtt out","z":"ee314869.f86738","name":"","topic":"/v1/{your Device Id}/data","qos":"","retain":"","broker":"3b957dc9.63628a","x":754,"y":822.6944580078125,"wires":[]},{"id":"fbb0f462.19767","type":"function","z":"ee314869.f86738","name":"relayr Payload Formatting","func":"msg.payload = {\n    meaning: 'capacitance',\n    value: msg.payload\n}\nreturn msg;","outputs":1,"noerr":0,"x":555.4722290039062,"y":752.0277709960938,"wires":[["14f1bbc7.9e90c4"]]},{"id":"c23e79f0.d14e","type":"function","z":"ee314869.f86738","name":"Read Capacitance","func":"msg.payload = msg.payload[0];\nreturn msg;","outputs":1,"noerr":0,"x":383.6944580078125,"y":675.75,"wires":[["fbb0f462.19767","23f2374.cd72148"]]},{"id":"781acd14.1ef4dc","type":"function","z":"ee314869.f86738","name":"Exception","func":"if (msg.payload < 32000)\n{\n    return msg;\n}","outputs":1,"noerr":0,"x":511.75,"y":206.25,"wires":[["a6ffe5ed.8948d8","1f3cc0d.2f72b3f"]]},{"id":"1f3cc0d.2f72b3f","type":"debug","z":"ee314869.f86738","name":"","active":false,"console":"false","complete":"false","x":722.75,"y":153.25,"wires":[]},{"id":"23f2374.cd72148","type":"debug","z":"ee314869.f86738","name":"","active":false,"console":"false","complete":"false","x":626.75,"y":652.25,"wires":[]},{"id":"8bde0f02.d34bd","type":"modbustcp-server","z":"ee314869.f86738","host":"192.168.1.250","port":"502","unit_id":"1"},{"id":"3b957dc9.63628a","type":"mqtt-broker","z":"ee314869.f86738","broker":"mqtt.relayr.io","port":"8883","tls":"","clientid":"","usetls":true,"compatmode":false,"keepalive":"60","cleansession":true,"willTopic":"","willQos":"0","willRetain":"false","willPayload":"","birthTopic":"","birthQos":"0","birthRetain":"false","birthPayload":""},{"id":"39858602.52a1a2","type":"modbustcp-server","z":"ee314869.f86738","host":"192.168.1.250","port":"502","unit_id":"1"},{"id":"a1959601.692438","type":"modbustcp-server","z":"ee314869.f86738","host":"192.168.1.250","port":"502","unit_id":"1"}]